{
    "scores": [
        {
            "kills": 126,
            "ultras": [ ],
            "subarea": 1,
            "mutations": [
                "Confidence",
                11,
                "Sadism"
            ],
            "time": 6210,
            "pizzas": 1,
            "race": 14,
            "allies": [
                {
                    "alias": "Dibble",
                    "wep": "va_sinusoid_pistol",
                    "bwep": 7,
                    "race": 14,
                    "color": 9532927,
                    "skin": 0
                }
            ],
            "name": "Dibble",
            "killed_by": 49,
            "bwep": 7,
            "wep": "va_sinusoid_pistol",
            "hard": 6,
            "loop": 0,
            "crown": false,
            "loadout": [
                {
                    "alias": "Dibble",
                    "wep": "mw_ui_start",
                    "bwep": 0,
                    "race": 14,
                    "color": 9532927,
                    "skin": 0
                }
            ],
            "color": 9532927,
            "area": 3,
            "skin": 0
        },
        {
            "kills": 61,
            "ultras": [ ],
            "subarea": 3,
            "mutations": [
                "Confidence"
            ],
            "time": 1892,
            "pizzas": 0,
            "race": 14,
            "allies": [
                {
                    "alias": "Dibble",
                    "wep": 56,
                    "bwep": 7,
                    "race": 14,
                    "color": 9532927,
                    "skin": 0
                }
            ],
            "name": "Dibble",
            "killed_by": 6,
            "bwep": 7,
            "wep": 56,
            "hard": 3,
            "loop": 0,
            "crown": false,
            "loadout": [
                {
                    "alias": "Dibble",
                    "wep": "mw_ui_start",
                    "bwep": 0,
                    "race": 14,
                    "color": 9532927,
                    "skin": 0
                }
            ],
            "color": 9532927,
            "area": 1,
            "skin": 0
        }
    ]
}