{
    "scores": [
        {
            "kills": 704,
            "bwep": 111,
            "hard": 20,
            "subarea": 2,
            "area": 1,
            "name": "Jaz-I-Lantern",
            "loadout": [
                {
                    "skin": 1,
                    "alias": "Jaz-I-Lantern",
                    "race": 6,
                    "color": 13281508,
                    "wep": "mw_ui_start",
                    "bwep": 0
                }
            ],
            "skin": 1,
            "crown": 1,
            "allies": [
                {
                    "skin": 1,
                    "alias": "Jaz-I-Lantern",
                    "race": 6,
                    "color": 13281508,
                    "wep": 40,
                    "bwep": 111
                }
            ],
            "race": 6,
            "pizzas": 0,
            "color": 13281508,
            "time": 27845,
            "wep": 40,
            "ultras": [
                [
                    6,
                    1
                ]
            ],
            "loop": 1,
            "killed_by": 51,
            "mutations": [
                10,
                13,
                4,
                3,
                23,
                "Thick Head",
                "Sadism",
                "Loner",
                "Dynamic Calves"
            ]
        },
        {
            "kills": 1231,
            "bwep": 111,
            "hard": 30,
            "subarea": 2,
            "area": 5,
            "name": "SPC",
            "loadout": [
                {
                    "skin": 0,
                    "alias": "SPC",
                    "race": 14,
                    "color": 4261187,
                    "wep": "mw_ui_start",
                    "bwep": 0
                }
            ],
            "crown": 7,
            "skin": 0,
            "allies": [
                {
                    "skin": 0,
                    "alias": "SPC",
                    "race": 9,
                    "color": 4261187,
                    "wep": 24,
                    "bwep": 111
                }
            ],
            "race": 9,
            "pizzas": 1,
            "color": 4261187,
            "time": 41753,
            "wep": 24,
            "ultras": [
                [
                    9,
                    2
                ]
            ],
            "loop": 1,
            "killed_by": -1,
            "mutations": [
                "Reincarnation",
                13,
                1,
                17,
                "concentration",
                7,
                "Confidence",
                3,
                27,
                "Thick Head",
                "Slim Pickings",
                "Free Space",
                "Laser Focus",
                "Iron Skin",
                "Loner",
                "Rubber Rounds",
                14
            ]
        },
        {
            "kills": 280,
            "bwep": 80,
            "hard": 14,
            "subarea": 3,
            "area": 5,
            "name": "SPC",
            "loadout": [
                {
                    "skin": 1,
                    "alias": "SPC",
                    "race": 4,
                    "color": 4261187,
                    "wep": "mw_ui_start",
                    "bwep": 0
                }
            ],
            "crown": 11,
            "skin": 1,
            "allies": [
                {
                    "skin": 1,
                    "alias": "SPC",
                    "race": 4,
                    "color": 4261187,
                    "wep": "sonic hammer",
                    "bwep": 80
                }
            ],
            "race": 4,
            "pizzas": 1,
            "color": 4261187,
            "time": 27934,
            "wep": "sonic hammer",
            "ultras": [ ],
            "loop": 0,
            "killed_by": 24,
            "mutations": [
                13,
                3,
                17,
                "concentration",
                "condensedmeat",
                25,
                23
            ]
        }
    ]
}