{"scores":[{"kills":6,"mutations":[],"subarea":1,"time":315,"allies":[{"color":5623039,"bwep":0,"wep":1,"alias":"Golden Epsilon","race":"fish","skin":0}],"race":"fish","name":"Golden Epsilon","color":5623039,"bwep":0,"wep":1,"killed_by":4,"hard":1,"loop":0,"crown":1,"area":1,"skin":0},{"mutations":[],"kills":0,"subarea":1,"allies":[{"color":5623039,"bwep":0,"wep":1,"alias":"Golden Epsilon","race":"fish","skin":0}],"time":559,"race":"fish","name":"Golden Epsilon","color":5623039,"bwep":0,"wep":1,"killed_by":4,"hard":1,"loop":0,"crown":1,"area":1,"skin":0}]}