{
    "scores": [
        {
            "kills": 3000,
            "subarea": 3,
            "ultras": [
                [
                    7,
                    1
                ]
            ],
            "mutations": [
                10,
                21,
                "Double Vision",
                "Absorbing Abs",
                5,
                "Mimicry",
                27,
                8
            ],
            "time": 60723,
            "pizzas": 0,
            "race": 7,
            "name": "Chump",
            "loadout": [
                {
                    "alias": "Chump",
                    "bwep": 1,
                    "wep": "mw_ui_start",
                    "race": 7,
                    "color": 16736708,
                    "skin": 0
                }
            ],
            "killed_by": 5,
            "bwep": "va_automagic_bolt_caster",
            "wep": "va_automagic_bolt_caster",
            "hard": 54,
            "loop": 3,
            "crown": 1,
            "allies": [
                {
                    "alias": "Chump",
                    "bwep": "va_automagic_bolt_caster",
                    "wep": "va_automagic_bolt_caster",
                    "race": 7,
                    "color": 16736708,
                    "skin": 0
                }
            ],
            "color": 16736708,
            "area": 1,
            "skin": 0
        },
        {
            "kills": 175,
            "ultras": [ ],
            "subarea": 2,
            "mutations": [
                "Slim Pickings",
                "Cranial Valve",
                "Laser Focus",
                23,
                5
            ],
            "time": 6418,
            "pizzas": 0,
            "race": 7,
            "loadout": [
                {
                    "alias": "Chump",
                    "wep": "mw_ui_start",
                    "bwep": 1,
                    "race": 7,
                    "color": 16736708,
                    "skin": 0
                }
            ],
            "name": "Chump",
            "killed_by": 15,
            "bwep": 2,
            "wep": 6,
            "hard": 6,
            "loop": 0,
            "crown": false,
            "allies": [
                {
                    "alias": "Chump",
                    "wep": 6,
                    "bwep": 2,
                    "race": 7,
                    "color": 16736708,
                    "skin": 0
                }
            ],
            "color": 16736708,
            "area": 3,
            "skin": 0
        }
    ]
}